drtools/__init__.py
drtools/file_manager.py
drtools/logging.py
drtools/retry.py
drtools/thread_pool_executor.py
drtools/types.py
drtools/utils.py
drtools/data_science/__init__.py
drtools/data_science/data_load.py
drtools/data_science/features.py
drtools/data_science/model.py
drtools/data_science/plot.py
drtools/data_science/time_series.py
drtools/data_science/transform.py
drtools/data_science/utils.py
drtools/database/__init__.py
drtools/database/utils.py
drtools/database/connection/__init__.py
drtools/database/connection/postgresql.py
drtools/database/connection/resources.py
drtools/database/extraction/__init__.py
drtools/database/extraction/massive.py
drtools/etl/__init__.py
drtools/etl/etl.py
drtools/etl/request.py
drtools/etl/resources.py
drtools/etl/types.py
drtools/etl/workflow.py
drtools/google/__init__.py
drtools/google/drive/__init__.py
drtools/google/drive/drive.py
drtools/google/drive/types.py
drtools/google/drive/utils.py
drtools/web_automation/__init__.py
drtools/web_automation/automation.py
drtools/web_automation/bot_detection.py
drtools/web_automation/exceptions.py
drtools/web_automation/types.py
drtools/web_automation/utils.py
drtools/web_automation/driver_handler/__init__.py
drtools/web_automation/driver_handler/chrome.py
drtools/web_automation/driver_handler/config.py
drtools/web_automation/driver_handler/handler.py
drtools/web_automation/gallery/__init__.py
drtools/web_automation/gallery/ecommerce_product.py
drtools-3.4.0.dist-info/licenses/LICENSE
drtools-3.4.0.dist-info/METADATA
drtools-3.4.0.dist-info/WHEEL
drtools-3.4.0.dist-info/top_level.txt
drtools-3.4.0.dist-info/RECORD
