Metadata-Version: 2.4
Name: drtools
Version: 3.4.0
Summary: Kit of MY useful tools.
Home-page: https://github.com/andreylcj/drtools
Author: Andrey Malheiros
Author-email: andreylcj@email.com
Project-URL: repository, https://github.com/andreylcj/drtools
Classifier: Programming Language :: Python :: 3
Classifier: License :: OSI Approved :: MIT License
Classifier: Operating System :: OS Independent
Requires-Python: >=3.8
License-File: LICENSE
Dynamic: license-file
